MANIFEST.in
license.md
readme.md
requirements.txt
setup.cfg
setup.py
chatterbot_corpus/__init__.py
chatterbot_corpus/corpus.py
chatterbot_corpus/data/bangla/botprofile.yml
chatterbot_corpus/data/bangla/computer.yml
chatterbot_corpus/data/bangla/emotions.yml
chatterbot_corpus/data/bangla/greetings.yml
chatterbot_corpus/data/chinese/ai.yml
chatterbot_corpus/data/chinese/botprofile.yml
chatterbot_corpus/data/chinese/conversations.yml
chatterbot_corpus/data/chinese/emotion.yml
chatterbot_corpus/data/chinese/food.yml
chatterbot_corpus/data/chinese/gossip.yml
chatterbot_corpus/data/chinese/greetings.yml
chatterbot_corpus/data/chinese/history.yml
chatterbot_corpus/data/chinese/humor.yml
chatterbot_corpus/data/chinese/literature.yml
chatterbot_corpus/data/chinese/money.yml
chatterbot_corpus/data/chinese/movies.yml
chatterbot_corpus/data/chinese/politics.yml
chatterbot_corpus/data/chinese/psychology.yml
chatterbot_corpus/data/chinese/science.yml
chatterbot_corpus/data/chinese/sports.yml
chatterbot_corpus/data/chinese/trivia.yml
chatterbot_corpus/data/custom/myown.yml
chatterbot_corpus/data/english/ai.yml
chatterbot_corpus/data/english/botprofile.yml
chatterbot_corpus/data/english/computers.yml
chatterbot_corpus/data/english/conversations.yml
chatterbot_corpus/data/english/emotion.yml
chatterbot_corpus/data/english/food.yml
chatterbot_corpus/data/english/gossip.yml
chatterbot_corpus/data/english/greetings.yml
chatterbot_corpus/data/english/health.yml
chatterbot_corpus/data/english/history.yml
chatterbot_corpus/data/english/humor.yml
chatterbot_corpus/data/english/literature.yml
chatterbot_corpus/data/english/money.yml
chatterbot_corpus/data/english/movies.yml
chatterbot_corpus/data/english/politics.yml
chatterbot_corpus/data/english/psychology.yml
chatterbot_corpus/data/english/science.yml
chatterbot_corpus/data/english/sports.yml
chatterbot_corpus/data/english/trivia.yml
chatterbot_corpus/data/french/botprofile.yml
chatterbot_corpus/data/french/conversations.yml
landa_chatterbot_corpus.egg-info/PKG-INFO
landa_chatterbot_corpus.egg-info/SOURCES.txt
landa_chatterbot_corpus.egg-info/dependency_links.txt
landa_chatterbot_corpus.egg-info/not-zip-safe
landa_chatterbot_corpus.egg-info/requires.txt
landa_chatterbot_corpus.egg-info/top_level.txt