Metadata-Version: 1.1
Name: landa-chatterbot-corpus
Version: 1.2.0
Summary: A machine readable multilingual dialog corpus
Home-page: https://github.com/gunthercox/chatterbot-corpus
Author: Gunther Cox
Author-email: gunthercx@gmail.com
License: BSD
Download-URL: https://github.com/gunthercox/chatterbot-corpus/tarball/1.2.0
Keywords: chatterbot,dialog,language,corpus
Platform: any
Classifier: Development Status :: 4 - Beta
Classifier: Intended Audience :: Developers
Classifier: License :: OSI Approved :: BSD License
Classifier: Environment :: Console
Classifier: Environment :: Web Environment
Classifier: Operating System :: OS Independent
Classifier: Topic :: Software Development :: Libraries :: Python Modules
Classifier: Topic :: Communications :: Chat
Classifier: Topic :: Internet
Classifier: Programming Language :: Python
Classifier: Programming Language :: Python :: 3
Classifier: Programming Language :: Python :: 3.4
Classifier: Programming Language :: Python :: 3.5
Classifier: Programming Language :: Python :: 3.6
Classifier: Programming Language :: Python :: 3.7
